odoo/addons/base_url/README.rst
odoo/addons/base_url/__init__.py
odoo/addons/base_url/__manifest__.py
odoo/addons/base_url/i18n/base_url.pot
odoo/addons/base_url/models/__init__.py
odoo/addons/base_url/models/abstract_url.py
odoo/addons/base_url/models/url_url.py
odoo/addons/base_url/security/ir.model.access.csv
odoo/addons/base_url/tests/__init__.py
odoo/addons/base_url/tests/models.py
odoo/addons/base_url/tests/models_mixin.py
odoo/addons/base_url/tests/test_abstract_url.py
odoo/addons/base_url/views/url_view.xml
odoo13_addon_base_url-13.0.1.2.0.dist-info/METADATA
odoo13_addon_base_url-13.0.1.2.0.dist-info/WHEEL
odoo13_addon_base_url-13.0.1.2.0.dist-info/top_level.txt
odoo13_addon_base_url-13.0.1.2.0.dist-info/RECORD
