Metadata-Version: 2.1
Name: odoo13-addon-base-url
Version: 13.0.1.2.0
Summary: keep history of url for products & categories
Home-page: https://github.com/shopinvader/odoo-shopinvader
Author: Akretion, ACSONE SA/NV
License: AGPL-3
Platform: UNKNOWN
Classifier: Programming Language :: Python
Classifier: Framework :: Odoo
Classifier: Framework :: Odoo :: 13.0
Classifier: License :: OSI Approved :: GNU Affero General Public License v3
Requires-Python: >=3.5
Requires-Dist: odoo (<13.1dev,>=13.0a)
Requires-Dist: python-slugify (>=3.0.2)
